glustercli/__init__.py
glustercli/_version.py
glustercli/cli/__init__.py
glustercli/cli/bitrot.py
glustercli/cli/bricks.py
glustercli/cli/georep.py
glustercli/cli/gluster_version.py
glustercli/cli/heal.py
glustercli/cli/nfs_ganesha.py
glustercli/cli/parsers.py
glustercli/cli/peer.py
glustercli/cli/quota.py
glustercli/cli/rebalance.py
glustercli/cli/snapshot.py
glustercli/cli/utils.py
glustercli/cli/volume.py
glustercli/metrics/__init__.py
glustercli/metrics/cmdlineparser.py
glustercli/metrics/diskstats.py
glustercli/metrics/process.py
glustercli/metrics/utilization.py
glustercli/metrics/utils.py
glustercli-0.8.6.dist-info/COPYING-GPLV2
glustercli-0.8.6.dist-info/COPYING-LGPLV3
glustercli-0.8.6.dist-info/METADATA
glustercli-0.8.6.dist-info/WHEEL
glustercli-0.8.6.dist-info/top_level.txt
glustercli-0.8.6.dist-info/RECORD
